{
"type": "FeatureCollection",
"name": "trees",
"crs": { "type": "name", "properties": { "name": "urn:ogc:def:crs:OGC:1.3:CRS84" } },
"features": [
{ "type": "Feature", "properties": { "osm_id": 5269763335, "natural": "tree" }, "geometry": { "type": "Point", "coordinates": [ 74.7932754, 13.0107062 ] } },
{ "type": "Feature", "properties": { "osm_id": 5269763336, "natural": "tree" }, "geometry": { "type": "Point", "coordinates": [ 74.793356, 13.0107155 ] } },
{ "type": "Feature", "properties": { "osm_id": 5269763337, "natural": "tree" }, "geometry": { "type": "Point", "coordinates": [ 74.7934883, 13.0106987 ] } },
{ "type": "Feature", "properties": { "osm_id": 5269763341, "natural": "tree" }, "geometry": { "type": "Point", "coordinates": [ 74.793354, 13.0108949 ] } },
{ "type": "Feature", "properties": { "osm_id": 5269763342, "natural": "tree" }, "geometry": { "type": "Point", "coordinates": [ 74.7934308, 13.0108987 ] } },
{ "type": "Feature", "properties": { "osm_id": 5269763343, "natural": "tree" }, "geometry": { "type": "Point", "coordinates": [ 74.793542, 13.0108874 ] } },
{ "type": "Feature", "properties": { "osm_id": 5269763338, "natural": "tree" }, "geometry": { "type": "Point", "coordinates": [ 74.7935727, 13.0107043 ] } },
{ "type": "Feature", "properties": { "osm_id": 5269763339, "natural": "tree" }, "geometry": { "type": "Point", "coordinates": [ 74.7936762, 13.0106856 ] } },
{ "type": "Feature", "properties": { "osm_id": 5269763340, "natural": "tree" }, "geometry": { "type": "Point", "coordinates": [ 74.7938047, 13.0107006 ] } },
{ "type": "Feature", "properties": { "osm_id": 5269763344, "natural": "tree" }, "geometry": { "type": "Point", "coordinates": [ 74.7936571, 13.0108893 ] } },
{ "type": "Feature", "properties": { "osm_id": 5269763345, "natural": "tree" }, "geometry": { "type": "Point", "coordinates": [ 74.793776, 13.010893 ] } }
]
}
